{
    "name": "Axivity_Postproc",
    "description": "A container to run accelerometry analyses on BIDS formatted data for HBCD.",
    "tool-version": "1.0",
    "schema-version": "0.5",
    "url": "https://github.com/erikglee/HBCD_Raw_Anat_QC_Container",
    "command-line": "true [DERIVATIVES_PREFIX]; axivity_postproc [SUBJECT_DIR] [POSTRPOC_OUTPUT_DIR] participant [SESSION_ID] [INTERVAL] [PA_MEASURE] [PA_SIDE] [ENTROPY_TYPE] [ENTROPY_MEASURE]",
    "container-image": {
        "image": "dcanumn/axivity_postproc:1.0",
        "index": "docker://",
        "type": "singularity"
    },
    "inputs": [
        {
            "description": "Subject folder for BIDS (folders name should be sub-XXXXX).",
            "id": "subject_dir",
            "name": "Subject Directory",
            "optional": false,
            "type": "File",
            "value-key": "[SUBJECT_DIR]"
        },
        {
            "description": "The name of the output folder. When processing is ran via CBRAIN only subject-specific files/folders will be saved, so the naming of the output folder will not influence the final naming/destination of files/folders.",
            "id": "postproc_output_dir",
            "name": "Postproc Output Directory",
            "optional": false,
            "type": "String",
            "value-key": "[POSTRPOC_OUTPUT_DIR]"
        },
        {
            "command-line-flag": "--session-id",
            "id": "session_id",
            "name": "Session ID",
            "description": "filter input dataset by session id",
            "optional": true,
            "type": "String",
            "value-key": "[SESSION_ID]"
        },
        {
            "command-line-flag": "--interval",
            "id": "interval",
            "name": "Interval",
            "description": "The label to correct or not the uneven sampling interval (raw or corrected)",
            "optional": true,
            "type": "String",
            "value-key": "[INTERVAL]"
        },
        {
            "command-line-flag": "--pa_measure",
            "id": "pa_measure",
            "name": "PA Measure",
            "description": "The computedQttyOption value (acceleration or jerk)",
            "optional": true,
            "type": "String",
            "value-key": "[PA_MEASURE]"
        },
        {
            "command-line-flag": "--pa_side",
            "id": "pa_side",
            "name": "PA Side",
            "description": "Which leg to calculate the physical activity level (Left/L or Right/R)",
            "optional": true,
            "type": "String",
            "value-key": "[PA_SIDE]"
        },
        {
            "command-line-flag": "--entropy_type",
            "id": "entropy_type",
            "name": "Entropy Type",
            "description": "Entropy type (SampEn or FuzzEn)",
            "optional": true,
            "type": "String",
            "value-key": "[ENTROPY_TYPE]"
        },
        {
            "command-line-flag": "--entropy_measure",
            "id": "entropy_measure",
            "name": "Entropy Measure",
            "description": "Measure to calculate an entropy (avgacc or pkacc)",
            "optional": true,
            "type": "String",
            "value-key": "[ENTROPY_MEASURE]"
        },
        {
            "default-value": "derivatives/",
            "id": "derivatives_prefix",
            "name": "derivatives_prefix",
            "description": "Folders to put before the pipeline specific folder. By default this will look like DataProvider/derivatives/PipelineName, where pipeline name is specific to the current pipeline. The provided string must end in /",
            "optional": true,
            "type": "String",
            "value-key": "[DERIVATIVES_PREFIX]"
        }
    ],
    "output-files" : [{
        "id" : "output_dir",
        "name" : "Output Directory",
        "description" : "This is the output containing the subject directory.",
        "path-template" : "[POSTRPOC_OUTPUT_DIR]/[SUBJECT_DIR]",
        "optional" : false
    }],
    "tags": {
        "application-type": [
            "bids"
        ],
        "domain": [
            "accelerometry",
            "wearables",
            "bids"
        ]
    },
    "suggested-resources": {
        "cpu-cores": 1,
        "ram": 16,
        "walltime-estimate": 7000
    },
    "custom": {
        "cbrain:readonly-input-files": true,
        "cbrain:author": "Erik Lee <leex6144@umn.edu>",
        "cbrain:allow_empty_strings": ["derivatives_prefix"],
        "cbrain:no-run-id-for-outputs": [ "output_dir"],
        "cbrain:integrator_modules": {
            "BoutiquesFileTypeVerifier": {
                "subject_dir": [ "BidsSubject" ]
            },
            "BoutiquesFileNameMatcher": {
                "subject_dir": "^sub-[a-zA-Z0-9_]+$"
            },
            "BoutiquesOutputFileTypeSetter": {
                "output_dir": "AxivityPostprocOutput"
            },
            "BoutiquesTaskLogsCopier": {
                "stdout":     "[POSTRPOC_OUTPUT_DIR]/[SUBJECT_DIR]/.cbrain/stdout.log",
                "stderr":     "[POSTRPOC_OUTPUT_DIR]/[SUBJECT_DIR]/.cbrain/stderr.log",
                "runtime":    "[POSTRPOC_OUTPUT_DIR]/[SUBJECT_DIR]/.cbrain/runtime_info.properties",
                "descriptor": "[POSTRPOC_OUTPUT_DIR]/[SUBJECT_DIR]/.cbrain/boutiques_descriptor.json",
                "invoke":     "[POSTRPOC_OUTPUT_DIR]/[SUBJECT_DIR]/.cbrain/boutiques_invoke.json",
                "jobscript":  "[POSTRPOC_OUTPUT_DIR]/[SUBJECT_DIR]/.cbrain/job_script.sh",
                "cbrain_params": "[POSTRPOC_OUTPUT_DIR]/[SUBJECT_DIR]/.cbrain/cbrain_params.json"
            },
            "BoutiquesForcedOutputBrowsePath" : {
              "output_dir": "[DERIVATIVES_PREFIX]axivity_postproc"
            },
            "BoutiquesBidsSingleSubjectMaker": "subject_dir",
            "BoutiquesBidsSubjectFileSelector": { "subject_dir": "all_to_keep" }
        }
    }
}